trivector/__init__.py
trivector/__main__.py
trivector/trivector.py
trivector-1.1.1.dist-info/LICENSE
trivector-1.1.1.dist-info/METADATA
trivector-1.1.1.dist-info/WHEEL
trivector-1.1.1.dist-info/entry_points.txt
trivector-1.1.1.dist-info/top_level.txt
trivector-1.1.1.dist-info/RECORD
