Metadata-Version: 2.1
Name: trivector
Version: 1.1.1
Summary: Convert an image into a SVG vector image composed of triangular sectors.
Home-page: https://github.com/nklapste/trivector
Author: Nathan Klapstein
Author-email: nklapste@ualberta.ca
License: MIT
Platform: UNKNOWN
Classifier: License :: OSI Approved :: MIT License
Classifier: Programming Language :: Python :: 3
Classifier: Programming Language :: Python :: 3.5
Classifier: Programming Language :: Python :: 3.6
Classifier: Programming Language :: Python :: 3.7
Classifier: Topic :: Multimedia :: Graphics :: Editors :: Vector-Based
Classifier: Topic :: Multimedia :: Graphics :: Graphics Conversion
Requires-Dist: svgwrite (<2.0.0,>=1.1.12)
Requires-Dist: opencv-python (<4.0.0.0,>=3.4.1.15)
Requires-Dist: numpy (<2.0.0,>=1.14.3)
Requires-Dist: progressbar2 (<4.0.0,>=3.37.1)
Provides-Extra: docs
Requires-Dist: sphinx (<2.0.0,>=1.7.5) ; extra == 'docs'
Requires-Dist: sphinx-rtd-theme (<1.0.0,>=0.3.1) ; extra == 'docs'
Requires-Dist: sphinx-autodoc-typehints (<2.0.0,>=1.3.0) ; extra == 'docs'
Requires-Dist: sphinx-argparse (<1.0.0,>=0.2.2) ; extra == 'docs'
